{
    "SUCCESS": true,
    "EXHIBITOR": {
        "DISPLAY_ORDER": 1,
        "BOOTHS": [
            {
                "BOOTH_NO": 1925,
                "BOOTH_KEY": "07FD6896-AC88-43D1-B107-A6D060C308B4",
                "KEY_ID": "22940031-EBFD-9ABA-7918-0CF7BDF8862A"
            }
        ],
        "BOOKMARKED": 0,
        "KEY_ID": "C22137CB-98C3-EF11-8101-8147A53E1DD0",
        "PRIMARY_BOOTH": 1925,
        "EXHIBITOR_TYPE": "Primary",
        "COMPANY_NAME": "Endeavor 3D",
        "FORM_KEY": "9564C846-215F-4280-94E1-8DF7D71CEF5F",
        "STATUS": 3,
        "DIRECTORY": {
            "FACEBOOK": "",
            "INSTAGRAM": "",
            "ACTIVE": 1,
            "ZIP_CODE": 30134,
            "TIKTOK": "",
            "PHONE": "",
            "LOGO": "https://eshow.sfo2.cdn.digitaloceanspaces.com/DC193D29-E3B4-EE11-A2F9-00155D57F530/1001/2024122610243_94b27e66498d92bb15ad609640069279.png",
            "STATE": "GA",
            "LAST_NAME": "",
            "DIVISION": "",
            "FIRST_NAME": "",
            "CREDENTIALS": "",
            "COUNTRY": "US",
            "SALUTATION": "",
            "DESCRIPTION": "Endeavor 3D is a leading provider of additive manufacturing solutions and is one of the largest 3D printing contract manufacturing partners in the southeast United States. Endeavor 3D specializes in product design, production, post-processing, and quality control of critical parts and assemblies in the medical device, consumer product, aerospace, and transportation markets. Endeavor 3D combines decades of manufacturing expertise with a cutting-edge 65,000-square-foot facility in Metro Atlanta, GA, to serve as a leading manufacturing partner across sectors. Endeavor 3D is ITAR registered, ISO 9001-2015 certified, and is an HP Digital Manufacturing Network Partner, certified for best-in-class quality, volume production at scale, and robust quality management.",
            "CATEGORY": [
                {
                    "ANSWER_KEY": "7401C345-EAE6-EE11-8100-B0DE0BDD54BD",
                    "ACTIVE": 1,
                    "RESPONSE_TEXT": "",
                    "KEY_ID": "6D73C3D1-A1A3-6C7C-C4B7-BCC8DB57BDA7",
                    "ANSWER_TITLE": "Manufacturing Machinery/Contract Manufacturing/Production Equipment"
                }
            ],
            "ADDRESS1": "",
            "ADDRESS2": "",
            "MAP_LOGO": true,
            "LINKEDIN": "",
            "SURVEYS": [
                {
                    "QUESTION_NAME": "Pavilion Name",
                    "RESPONSES": [
                        {
                            "ANSWER_KEY": "E4A34420-7061-EF11-8100-B0DE0BDD54BD",
                            "ACTIVE": 1,
                            "RESPONSE_TEXT": "",
                            "KEY_ID": "D0D4FCB3-EC45-5371-520D-DA52007F4886",
                            "ANSWER_TITLE": "Advanced Materials and Manufacturing"
                        }
                    ],
                    "NET_CODE": "",
                    "QUESTION_TYPE": 4,
                    "QUESTION_KEY": "243518A3-B98F-4668-972D-96B75DB85BAA"
                }
            ],
            "TOLL_FREE": "",
            "KEY_ID": "22BFA2D0-F998-9558-6857-21C4C5663EC8",
            "WORK_PHONE": "",
            "COMPANY_NAME": "Endeavor 3D",
            "CITY": "Douglasville",
            "BRAND_NAME": "",
            "TITLE": "",
            "FAX": "",
            "WEBSITE": "https://endeavor3d.com/",
            "TWITTER": ""
        },
        "BOOTH_SPACE_RESELLER": "",
        "GROUP_KEY": "",
        "CRM_COMPANY_KEY": "7DFC5CE8-2788-43D5-98B5-7A3E323A28B4"
    }
}